CHANGELOG.txt
LICENSE.txt
MANIFEST.in
README.md
setup.py
ordbhandler/__init__.py
ordbhandler/mysql_handler.py
ordbhandler.egg-info/PKG-INFO
ordbhandler.egg-info/SOURCES.txt
ordbhandler.egg-info/dependency_links.txt
ordbhandler.egg-info/requires.txt
ordbhandler.egg-info/top_level.txt