Metadata-Version: 2.1
Name: ordbhandler
Version: 0.0.1
Summary: RDMS Data Management.
Home-page: https://github.com/leonardomra/ordbhandler
Author: Leonardo de Araújo
Author-email: dearaujo@uni-bremen.de
License: UNKNOWN
Platform: UNKNOWN
Classifier: Programming Language :: Python :: 3
Classifier: License :: OSI Approved :: MIT License
Classifier: Operating System :: OS Independent
Requires-Python: >=3.6
